CHANGELOG.md
LICENSE
ksp_price_notifier/__init__.py
ksp_price_notifier/__main__.py
ksp_price_notifier/get_price.py
ksp_price_notifier-0.1.6.dist-info/entry_points.txt
ksp_price_notifier-0.1.6.dist-info/LICENSE
ksp_price_notifier-0.1.6.dist-info/WHEEL
ksp_price_notifier-0.1.6.dist-info/METADATA
ksp_price_notifier-0.1.6.dist-info/RECORD
