Metadata-Version: 2.1
Name: ksp-price-notifier
Version: 0.1.6
Summary: 
Home-page: https://github.com/jochman/KSP-Price-Notifier
License: MIT
Author: Jochman
Requires-Python: >=3.8,<4.0
Classifier: Development Status :: 2 - Pre-Alpha
Classifier: License :: OSI Approved :: MIT License
Classifier: Programming Language :: Python :: 3
Classifier: Programming Language :: Python :: 3.10
Classifier: Programming Language :: Python :: 3.8
Classifier: Programming Language :: Python :: 3.9
Requires-Dist: typer (>=0.4.0,<0.5.0)
Project-URL: Repository, https://github.com/jochman/KSP-Price-Notifier
